cds_trytond_product_uri-4.6.1.dist-info/DESCRIPTION.rst
cds_trytond_product_uri-4.6.1.dist-info/METADATA
cds_trytond_product_uri-4.6.1.dist-info/RECORD
cds_trytond_product_uri-4.6.1.dist-info/WHEEL
cds_trytond_product_uri-4.6.1.dist-info/entry_points.txt
cds_trytond_product_uri-4.6.1.dist-info/metadata.json
cds_trytond_product_uri-4.6.1.dist-info/top_level.txt
trytond/modules/product_uri/__init__.py
trytond/modules/product_uri/category.py
trytond/modules/product_uri/category.xml
trytond/modules/product_uri/template.py
trytond/modules/product_uri/template.xml
trytond/modules/product_uri/tryton.cfg
trytond/modules/product_uri/view/category_form.xml
trytond/modules/product_uri/view/category_tree.xml
trytond/modules/product_uri/view/template_form.xml
trytond/modules/product_uri/view/template_tree.xml
