Metadata-Version: 2.0
Name: cds-trytond-product-uri
Version: 4.6.1
Summary: Tryton module to add URI slugs to products
Home-page: https://src.coalesco.ca/tryton/modules/cds_trytond_product_uri
Author: Tryton
Author-email: it@coalesco.ca
License: GPL-3
Download-URL: https://src.coalesco.ca/tryton/modules/cds_trytond_product_uri/archive/tip.zip
Keywords: tryton product uri slug
Platform: UNKNOWN
Classifier: Development Status :: 5 - Production/Stable
Classifier: Environment :: Plugins
Classifier: Framework :: Tryton
Classifier: Intended Audience :: Developers
Classifier: Intended Audience :: Financial and Insurance Industry
Classifier: Intended Audience :: Legal Industry
Classifier: Intended Audience :: Manufacturing
Classifier: License :: OSI Approved :: GNU General Public License (GPL)
Classifier: Natural Language :: Bulgarian
Classifier: Natural Language :: English
Classifier: Operating System :: OS Independent
Classifier: Programming Language :: Python :: 2.7
Classifier: Programming Language :: Python :: 3.3
Classifier: Programming Language :: Python :: 3.4
Classifier: Programming Language :: Python :: 3.5
Classifier: Programming Language :: Python :: Implementation :: CPython
Classifier: Programming Language :: Python :: Implementation :: PyPy
Classifier: Topic :: Office/Business
Requires-Dist: python-sql
Requires-Dist: unicode-slugify
Requires-Dist: trytond-product (<4.7,>=4.6)
Requires-Dist: trytond (<4.7,>=4.6)
